cdk_minecraft_server/__init__.py
cdk_minecraft_server/py.typed
cdk_minecraft_server/_jsii/__init__.py
cdk_minecraft_server/_jsii/cdk-minecraft-server@0.0.4.jsii.tgz
cdk_minecraft_server-0.0.4.dist-info/LICENSE
cdk_minecraft_server-0.0.4.dist-info/METADATA
cdk_minecraft_server-0.0.4.dist-info/WHEEL
cdk_minecraft_server-0.0.4.dist-info/top_level.txt
cdk_minecraft_server-0.0.4.dist-info/RECORD
