Metadata-Version: 2.1
Name: cdk-minecraft-server
Version: 0.0.4
Summary: cdk-minecraft-server
Home-page: https://github.com/Weasledorf-Inc/cdk-minecraft-server
Author: Hasan Abu-Rayyan<hasanaburayyan21@gmail.com>
License: Apache-2.0
Project-URL: Source, https://github.com/Weasledorf-Inc/cdk-minecraft-server
Platform: UNKNOWN
Classifier: Intended Audience :: Developers
Classifier: Operating System :: OS Independent
Classifier: Programming Language :: JavaScript
Classifier: Programming Language :: Python :: 3 :: Only
Classifier: Programming Language :: Python :: 3.6
Classifier: Programming Language :: Python :: 3.7
Classifier: Programming Language :: Python :: 3.8
Classifier: Programming Language :: Python :: 3.9
Classifier: Typing :: Typed
Classifier: Development Status :: 5 - Production/Stable
Classifier: License :: OSI Approved
Requires-Python: >=3.6
License-File: LICENSE
Requires-Dist: aws-cdk.aws-apigatewayv2-integrations (<2.0.0,>=1.34.0)
Requires-Dist: aws-cdk.aws-apigatewayv2 (<2.0.0,>=1.34.0)
Requires-Dist: aws-cdk.aws-ec2 (<2.0.0,>=1.34.0)
Requires-Dist: aws-cdk.aws-ecr-assets (<2.0.0,>=1.34.0)
Requires-Dist: aws-cdk.aws-ecr (<2.0.0,>=1.34.0)
Requires-Dist: aws-cdk.aws-iam (<2.0.0,>=1.34.0)
Requires-Dist: aws-cdk.aws-lambda-nodejs (<2.0.0,>=1.34.0)
Requires-Dist: aws-cdk.aws-lambda-python (<2.0.0,>=1.34.0)
Requires-Dist: aws-cdk.aws-s3-deployment (<2.0.0,>=1.34.0)
Requires-Dist: aws-cdk.aws-s3 (<2.0.0,>=1.34.0)
Requires-Dist: aws-cdk.core (<2.0.0,>=1.34.0)
Requires-Dist: cdk-ecr-deployment (<0.0.88,>=0.0.87)
Requires-Dist: constructs (<4.0.0,>=3.2.27)
Requires-Dist: jsii (<2.0.0,>=1.46.0)
Requires-Dist: publication (>=0.0.3)
